dev3/__init__.py
dev3/nodev1.py
dev3-0.9.1.dist-info/METADATA
dev3-0.9.1.dist-info/WHEEL
dev3-0.9.1.dist-info/licenses/LICENSE
dev3-0.9.1.dist-info/RECORD
