Metadata-Version: 2.1
Name: dev3
Version: 0.9.1
Summary: A package to customize autonomous interfacing between different blockchains
Project-URL: Homepage, https://github.com/0xAetherLabs/dev3
Project-URL: Bug Tracker, https://github.com/0xAetherLabs/dev3/issues
Author-email: mrkj <kj@aetherlabs.io>
License: GNU GENERAL PUBLIC LICENSE
Classifier: License :: OSI Approved :: GNU General Public License v3 (GPLv3)
Classifier: Operating System :: OS Independent
Classifier: Programming Language :: Python :: 3
Requires-Python: >=3.7
